m3_simple_report-1.7.0.dist-info/licenses/LICENSE
simple_report/__init__.py
simple_report/interface.py
simple_report/report.py
simple_report/utils.py
simple_report/converter/__init__.py
simple_report/converter/abstract.py
simple_report/converter/open_office/__init__.py
simple_report/converter/open_office/settings.py
simple_report/converter/open_office/wrapper.py
simple_report/core/__init__.py
simple_report/core/cursor.py
simple_report/core/document_wrap.py
simple_report/core/exception.py
simple_report/core/shared_table.py
simple_report/core/spreadsheet_section.py
simple_report/core/tags.py
simple_report/core/xml_wrap.py
simple_report/docx/__init__.py
simple_report/docx/document.py
simple_report/docx/drawing.py
simple_report/docx/wordprocessing_ml.py
simple_report/rtf/__init__.py
simple_report/rtf/api.py
simple_report/rtf/document.py
simple_report/rtf/parser.py
simple_report/xls/__init__.py
simple_report/xls/cursor.py
simple_report/xls/document.py
simple_report/xls/output_options.py
simple_report/xls/section.py
simple_report/xls/workbook.py
simple_report/xlsx/__init__.py
simple_report/xlsx/cursor.py
simple_report/xlsx/document.py
simple_report/xlsx/formula.py
simple_report/xlsx/section.py
simple_report/xlsx/spreadsheet_ml.py
tests/__init__.py
tests/oborot.py
tests/test_core.py
tests/test_docx.py
tests/test_oo_wrapper.py
tests/test_pagebreaks.py
tests/test_pko.py
tests/test_rtf.py
tests/utils.py
tests/test_data/linux/docx/test-sluzh.docx
tests/test_data/linux/docx/test_divisibles.docx
tests/test_data/linux/docx/test_flush_order.docx
tests/test_data/linux/docx/test_insert_image.docx
tests/test_data/linux/docx/test_insert_image.jpg
tests/test_data/linux/docx/test_pict_shape_2.docx
tests/test_data/linux/docx/test_rect.docx
tests/test_data/linux/docx/test_spreadsheet.docx
tests/test_data/linux/docx/test_table.docx
tests/test_data/linux/docx/test_table_double_section.docx
tests/test_data/linux/docx/test_table_image.gif
tests/test_data/linux/docx/test_tabs.docx
tests/test_data/linux/docx/reference/test-sluzh.docx
m3_simple_report-1.7.0.dist-info/METADATA
m3_simple_report-1.7.0.dist-info/WHEEL
m3_simple_report-1.7.0.dist-info/dependency_links.txt
m3_simple_report-1.7.0.dist-info/top_level.txt
m3_simple_report-1.7.0.dist-info/RECORD
